forbidden/main.py
forbidden/utils/array.py
forbidden/utils/config.py
forbidden/utils/cookie.py
forbidden/utils/crypto.py
forbidden/utils/encode.py
forbidden/utils/file.py
forbidden/utils/forbidden.py
forbidden/utils/general.py
forbidden/utils/grep.py
forbidden/utils/header.py
forbidden/utils/ip.py
forbidden/utils/path.py
forbidden/utils/record.py
forbidden/utils/report.py
forbidden/utils/test.py
forbidden/utils/url.py
forbidden/utils/validate.py
forbidden/utils/value.py
forbidden-13.4.dist-info/licenses/LICENSE
stresser/main.py
stresser/utils/array.py
stresser/utils/config.py
stresser/utils/cookie.py
stresser/utils/directory.py
stresser/utils/encode.py
stresser/utils/file.py
stresser/utils/general.py
stresser/utils/grep.py
stresser/utils/header.py
stresser/utils/ip.py
stresser/utils/path.py
stresser/utils/record.py
stresser/utils/report.py
stresser/utils/stresser.py
stresser/utils/url.py
stresser/utils/validate.py
forbidden-13.4.dist-info/METADATA
forbidden-13.4.dist-info/WHEEL
forbidden-13.4.dist-info/entry_points.txt
forbidden-13.4.dist-info/top_level.txt
forbidden-13.4.dist-info/RECORD
