Metadata-Version: 2.4
Name: forbidden
Version: 13.4
Summary: Bypass 4xx HTTP response status codes and more.
Author: Ivan Sincek
Project-URL: Homepage, https://github.com/ivan-sincek/forbidden
Classifier: Programming Language :: Python :: 3
Classifier: License :: OSI Approved :: MIT License
Classifier: Operating System :: POSIX :: Linux
Requires-Python: >=3.10
License-File: LICENSE
Requires-Dist: alive-progress>=3.1.5
Requires-Dist: bot_safe_agents>=1.0
Requires-Dist: colorama>=0.4.6
Requires-Dist: cryptography>=44.0.1
Requires-Dist: pycurl>=7.45.2
Requires-Dist: pyjwt>=2.7.0
Requires-Dist: regex>=2023.8.8
Requires-Dist: requests>=2.32.2
Requires-Dist: tabulate>=0.9.0
Requires-Dist: termcolor>=2.4.0
Dynamic: license-file
